__init__.py
library_core/configure_logging.py
library_core/constants_lib.py
library_core/deploy.py
library_core/library_main.py
library_core/setup_or_check.py
library_core/tests/common_for_tests.py
library_core/tests/test_basic.py
library_core/tests/test_check_and_configure.py
mrodent_dev_lib-1.2.1.dist-info/METADATA
mrodent_dev_lib-1.2.1.dist-info/WHEEL
mrodent_dev_lib-1.2.1.dist-info/entry_points.txt
mrodent_dev_lib-1.2.1.dist-info/top_level.txt
mrodent_dev_lib-1.2.1.dist-info/RECORD
